inspectdb_refactor/__init__.py
inspectdb_refactor/apps.py
inspectdb_refactor/tests.py
inspectdb_refactor/admin/__init__.py
inspectdb_refactor/forms/__init__.py
inspectdb_refactor/management/__init__.py
inspectdb_refactor/management/commands/__init__.py
inspectdb_refactor/management/commands/inspectdb_refactor.py
inspectdb_refactor/migrations/__init__.py
inspectdb_refactor/models/__init__.py
inspectdb_refactor/views/__init__.py
django_inspectdb_refactor-0.4.dist-info/LICENSE
django_inspectdb_refactor-0.4.dist-info/METADATA
django_inspectdb_refactor-0.4.dist-info/WHEEL
django_inspectdb_refactor-0.4.dist-info/top_level.txt
django_inspectdb_refactor-0.4.dist-info/RECORD
