Metadata-Version: 1.1
Name: django-inspectdb-refactor
Version: 0.4
Summary: A simple Django app to create refactor output of inspectdb command into separate classes.
Home-page: https://github.com/farhan0581/django-inspectdb-refactor
Author: Farhan Khan
Author-email: farhan0581@gmail.com
License: BSD License
Platform: UNKNOWN
Classifier: Framework :: Django
Classifier: Framework :: Django :: 1.11
Classifier: Intended Audience :: Developers
Classifier: License :: OSI Approved :: BSD License
Classifier: Operating System :: OS Independent
Classifier: Programming Language :: Python
Classifier: Programming Language :: Python :: 2.7
Classifier: Programming Language :: Python :: 3.5
Classifier: Programming Language :: Python :: 3.6
Classifier: Topic :: Internet :: WWW/HTTP
Classifier: Topic :: Software Development :: Libraries :: Python Modules
